uda_xarray/main.py
uda_xarray-0.2.0.dist-info/licenses/LICENSE
uda_xarray-0.2.0.dist-info/METADATA
uda_xarray-0.2.0.dist-info/WHEEL
uda_xarray-0.2.0.dist-info/entry_points.txt
uda_xarray-0.2.0.dist-info/top_level.txt
uda_xarray-0.2.0.dist-info/RECORD
