Metadata-Version: 2.4
Name: uda-xarray
Version: 0.2.0
Summary: UDA backend for xarray
Author-email: Samuel Jackson <samuel.jackson@ukaea.uk>
Maintainer-email: Samuel Jackson <samuel.jackson@ukaea.uk>
Project-URL: repository, https://github.com/samueljackson92/uda-xarray
Classifier: Development Status :: 4 - Beta
Classifier: Programming Language :: Python :: 3
Classifier: Programming Language :: Python :: 3.11
Classifier: Programming Language :: Python :: 3.12
Classifier: License :: OSI Approved :: MIT License
Requires-Python: <3.13,>=3.11
License-File: LICENSE
Requires-Dist: uda>=2.9.2
Requires-Dist: uda-mast
Requires-Dist: xarray>=2025.12.0
Dynamic: license-file
